README.md
pyproject.toml
setup.cfg
setup.py
src/codewhisper/__init__.py
src/codewhisper/exceptions.py
src/codewhisper/grammar.c
src/codewhisper/parsing.c
src/codewhisper/special.c
src/codewhisper/tokens.c
src/codewhisper.egg-info/PKG-INFO
src/codewhisper.egg-info/SOURCES.txt
src/codewhisper.egg-info/dependency_links.txt
src/codewhisper.egg-info/not-zip-safe
src/codewhisper.egg-info/top_level.txt