Metadata-Version: 2.1
Name: codewhisper
Version: 1.1.0
Summary: Dynamic parsing library
Home-page: https://gitlab.com/goldenleaf/codewhisper
Author: Eric Wald
Author-email: codewhisper@brainshell.org
License: MIT
Classifier: Development Status :: 5 - Production/Stable
Classifier: Intended Audience :: Developers
Classifier: License :: OSI Approved :: MIT License
Classifier: Programming Language :: Cython
Classifier: Programming Language :: Python :: 3
Classifier: Topic :: Text Processing :: General
Requires-Python: >=3.6
